NaStyAPI/APICall.py
NaStyAPI/Nation.py
NaStyAPI/Region.py
NaStyAPI/Telegrams.py
NaStyAPI/TradingCards.py
NaStyAPI/World.py
NaStyAPI/WorldAssembly.py
NaStyAPI/__init__.py
NaStyAPI-0.3.0.dist-info/LICENSE
NaStyAPI-0.3.0.dist-info/METADATA
NaStyAPI-0.3.0.dist-info/WHEEL
NaStyAPI-0.3.0.dist-info/top_level.txt
NaStyAPI-0.3.0.dist-info/RECORD
