Metadata-Version: 2.1
Name: NaStyAPI
Version: 0.3.0
Summary: A Python wrapper for the NationStates API
Home-page: UNKNOWN
Author: Roddy Rappaport
Author-email: Roddy.Rappaport@gmail.com
License: Apache License 2.0
Platform: UNKNOWN
Requires-Dist: requests (~=2.25.0)
Requires-Dist: ratelimit (~=2.2.1)
